odoo/addons/shopinvader_sale_coupon/README.rst
odoo/addons/shopinvader_sale_coupon/__init__.py
odoo/addons/shopinvader_sale_coupon/__manifest__.py
odoo/addons/shopinvader_sale_coupon/i18n/shopinvader_sale_coupon.pot
odoo/addons/shopinvader_sale_coupon/models/__init__.py
odoo/addons/shopinvader_sale_coupon/models/sale_order.py
odoo/addons/shopinvader_sale_coupon/services/__init__.py
odoo/addons/shopinvader_sale_coupon/services/abstract_sale.py
odoo/addons/shopinvader_sale_coupon/services/cart.py
odoo/addons/shopinvader_sale_coupon/services/customer.py
odoo/addons/shopinvader_sale_coupon/tests/__init__.py
odoo/addons/shopinvader_sale_coupon/tests/test_cart.py
odoo/addons/shopinvader_sale_coupon/tests/test_customer.py
odoo14_addon_shopinvader_sale_coupon-14.0.1.2.1.dist-info/METADATA
odoo14_addon_shopinvader_sale_coupon-14.0.1.2.1.dist-info/WHEEL
odoo14_addon_shopinvader_sale_coupon-14.0.1.2.1.dist-info/top_level.txt
odoo14_addon_shopinvader_sale_coupon-14.0.1.2.1.dist-info/RECORD
